triformer/__init__.py
triformer/cross_entropy.py
triformer/dropout.py
triformer/layernorm.py
triformer/rms_norm.py
triformer/rope.py
triformer/softmax.py
triformer/swiglu.py
triformer/utils.py
triformer-3.0.7.dist-info/LICENSE
triformer-3.0.7.dist-info/METADATA
triformer-3.0.7.dist-info/WHEEL
triformer-3.0.7.dist-info/top_level.txt
triformer-3.0.7.dist-info/RECORD
